{"imagePath":"C/texture.png","name":"start","SubTexture":[{"name":"other/3","x":116,"width":138,"y":168,"height":61},{"name":"other/8","x":0,"width":114,"y":168,"height":107},{"name":"other/7","x":0,"width":162,"y":0,"height":166},{"name":"other/9","x":327,"width":139,"y":166,"height":99},{"name":"other/11","x":164,"width":161,"y":0,"height":166},{"name":"other/4","x":327,"width":150,"y":0,"height":164},{"name":"other/6","x":116,"width":143,"y":231,"height":21},{"name":"other/5","x":355,"width":118,"y":267,"height":24},{"name":"other/13","x":239,"width":114,"y":267,"height":29},{"name":"other/1","x":0,"width":102,"y":277,"height":26},{"name":"other/12","x":104,"width":128,"y":282,"height":13},{"name":"other/10","x":355,"width":111,"y":293,"height":12},{"name":"other/2","x":116,"width":121,"y":254,"height":26}]}